sphinx_me.py
sphinx_me-0.3.data/scripts/sphinx-me
sphinx_me-0.3.dist-info/DESCRIPTION.rst
sphinx_me-0.3.dist-info/entry_points.txt
sphinx_me-0.3.dist-info/METADATA
sphinx_me-0.3.dist-info/pydist.json
sphinx_me-0.3.dist-info/RECORD
sphinx_me-0.3.dist-info/top_level.txt
sphinx_me-0.3.dist-info/WHEEL
